{"Graph":{"adjacencyMap":{"Privilege":{},"README":{},"Location agnosticism":{"Privilege":["cf",[]],"Loneliness in pandemic":["cf",[]],"homebridge-security-system to replicate actual alarm system":["cf",[]]},"Loneliness in pandemic":{},"Writing I am proud of":{},"Finished works":{},"Goals vs. systems":{},"homebridge-security-system to replicate actual alarm system":{},"Restaurants in 2025":{"Location agnosticism":["cf",[]]},"A bunch of crap duct-taped together":{},"Simplifying capture of ideas":{"Goals vs. systems":["cf",[]]},"Tools stack":{},"Create a new text file with clipboard content - Alfred":{"Simplifying capture of ideas":["cf",[]]},"TODO- Text expansion for backlink syntax":{"Simplifying capture of ideas":["cf",[]]},"posts":{},"TODO- Need a way to automatically push to the brain repo on mac":{"Simplifying capture of ideas":["cf",[]]},"Out of nowhere":{},"index":{"Writing I am proud of":["cf",[]],"Finished works":["cf",[]],"Tools stack":["cf",[]]}},"vertices":{"Privilege":{"Path":"./Privilege.md","Slug":"Privilege","ID":"Privilege","Meta":{"tags":[]},"Title":"Privilege"},"README":{"Path":"./README.md","Slug":"README","ID":"README","Meta":{"tags":["is_material"]},"Title":"How to publish your own neuron site"},"Location agnosticism":{"Path":"./Location agnosticism.md","Slug":"Location_agnosticism","ID":"Location agnosticism","Meta":{"tags":[]},"Title":"Location agnosticism"},"Loneliness in pandemic":{"Path":"./Loneliness in pandemic.md","Slug":"Loneliness_in_pandemic","ID":"Loneliness in pandemic","Meta":{"tags":[]},"Title":"Loneliness in pandemic"},"Writing I am proud of":{"Path":"./Writing I am proud of.md","Slug":"Writing_I_am_proud_of","ID":"Writing I am proud of","Meta":{"tags":[]},"Title":"Writing I am proud of"},"Finished works":{"Path":"./Finished works.md","Slug":"Finished_works","ID":"Finished works","Meta":{"tags":[]},"Title":"Finished works"},"Goals vs. systems":{"Path":"./Goals vs. systems.md","Slug":"Goals_vs._systems","ID":"Goals vs. systems","Meta":{"tags":[]},"Title":"Goals vs. systems"},"homebridge-security-system to replicate actual alarm system":{"Path":"./homebridge-security-system to replicate actual alarm system.md","Slug":"homebridge-security-system_to_replicate_actual_alarm_system","ID":"homebridge-security-system to replicate actual alarm system","Meta":{"tags":[]},"Title":"homebridge-security-system to replicate actual alarm system"},"Restaurants in 2025":{"Path":"./Restaurants in 2025.md","Slug":"Restaurants_in_2025","ID":"Restaurants in 2025","Meta":{"tags":[]},"Title":"Restaurants in 2025"},"A bunch of crap duct-taped together":{"Path":"./posts/A bunch of crap duct-taped together.md","Slug":"A_bunch_of_crap_duct-taped_together","ID":"A bunch of crap duct-taped together","Meta":{"tags":[]},"Title":"A bunch of crap duct-taped together"},"Simplifying capture of ideas":{"Path":"./Simplifying capture of ideas.md","Slug":"Simplifying_capture_of_ideas","ID":"Simplifying capture of ideas","Meta":{"tags":[]},"Title":"Simplifying capture of ideas"},"Tools stack":{"Path":"./Tools stack.md","Slug":"Tools_stack","ID":"Tools stack","Meta":{"tags":[]},"Title":"Tools stack"},"Create a new text file with clipboard content - Alfred":{"Path":"./Create a new text file with clipboard content - Alfred.md","Slug":"Create_a_new_text_file_with_clipboard_content_-_Alfred","ID":"Create a new text file with clipboard content - Alfred","Meta":{"tags":[]},"Title":"Create a new text file with clipboard content - Alfred"},"TODO- Text expansion for backlink syntax":{"Path":"./todo/TODO- Text expansion for backlink syntax.md","Slug":"TODO-_Text_expansion_for_backlink_syntax","ID":"TODO- Text expansion for backlink syntax","Meta":{"tags":[]},"Title":"TODO- Text expansion for backlink syntax"},"posts":{"Path":"./posts.md","Slug":"posts","ID":"posts","Meta":{"tags":[]},"Title":"posts"},"TODO- Need a way to automatically push to the brain repo on mac":{"Path":"./todo/TODO- Need a way to automatically push to the brain repo on mac.md","Slug":"TODO-_Need_a_way_to_automatically_push_to_the_brain_repo_on_mac","ID":"TODO- Need a way to automatically push to the brain repo on mac","Meta":{"tags":[]},"Title":"TODO- Need a way to automatically push to the brain repo on mac"},"Out of nowhere":{"Path":"./posts/Out of nowhere.md","Slug":"Out_of_nowhere","ID":"Out of nowhere","Meta":{"tags":[]},"Title":"Out of nowhere"},"index":{"Path":"./index.md","Slug":"index","ID":"index","Meta":{"tags":[]},"Title":"brandon lucas green"}}},"NeuronVersion":"1.9.27.0","Config":{"editUrl":null,"plugins":["neuronignore","links","tags","uptree","feed"],"siteBaseUrl":"https://brandonlucasgreen.github.io/brain","author":"brandon lucas green","siteTitle":"brandon lucas green","theme":"black"},"Errors":{"Privilege":{"tag":"ZettelIssue_MissingLinks","contents":["Privilege",["goals vs. systems","impostor syndrome","location agnosticism"]]},"README":{"tag":"ZettelIssue_MissingLinks","contents":["README",["faq"]]},"Goals vs. systems":{"tag":"ZettelIssue_MissingLinks","contents":["Goals_vs._systems",["Working out in the open"]]}}}